esther_args_history/__init__.py
esther_args_history-0.2.1.dist-info/METADATA
esther_args_history-0.2.1.dist-info/WHEEL
esther_args_history-0.2.1.dist-info/top_level.txt
esther_args_history-0.2.1.dist-info/RECORD
