Metadata-Version: 2.1
Name: esther_args_history
Version: 0.2.1
Summary: Default template for PDM package
Author-email: EstherCho-7 <dkgkqm777@gmail.com>
License: MIT
Project-URL: Homepages, https://github.com/EstherCho-7/esther_args_history.git
Project-URL: Issues, https://github.com/EstherCho-7/esther_args_history.git/issues
Requires-Python: ==3.11.*
